{"identificacaoPartida":"7cff7c37-cd07-4838-9368-c6004b3c3e07","quantidadeRodadas":12,"fatiaMercado":10000.0,"contadorRodadas":1,"partidaFinalizada":false,"rodadas":[{"identificacaoRodada":"1","jogadas":[{"identificacaoJogada":"1","demandaTotalJogada":1646,"preco":12.99,"notaPreco":6.750062546910183,"demandaPreco":1206,"investimentoPropagandaRadio":4000.0,"notaPropagandaRadio":3.085714285714286,"demandaPropagandaRadio":108,"investimentoPropagandaJornal":4000.0,"notaPropagandaJornal":2.238095238095238,"demandaPropagandaJornal":58,"investimentoPropagandaTV":4000.0,"notaPropagandaTV":2.111111111111111,"demandaPropagandaTV":64,"investimentoPropagandaInternet":8000.0,"notaPropagandaInternet":4.5,"demandaPropagandaInternet":180,"demandaTotalPropaganda":410,"qtdProdutosEstoqueFornecedor1":700,"qtdProdutosEstoqueFornecedor2":1100,"qtdProdutosEstoqueFornecedor3":950,"tamanhoEstabelecimento":"PEQUENO","qtdCaixas":3,"qtdFuncionarios":7,"pontosCapacidadeInstalada":70.0,"notaCapacidadeInstalada":1.001906577693041,"demandaCapacidadeInstalada":23},{"identificacaoJogada":"2","demandaTotalJogada":2090,"preco":12.99,"notaPreco":6.750062546910183,"demandaPreco":1206,"investimentoPropagandaRadio":0.0,"notaPropagandaRadio":0.0,"demandaPropagandaRadio":0,"investimentoPropagandaJornal":0.0,"notaPropagandaJornal":0.0,"demandaPropagandaJornal":0,"investimentoPropagandaTV":6000.0,"notaPropagandaTV":3.0,"demandaPropagandaTV":130,"investimentoPropagandaInternet":7500.0,"notaPropagandaInternet":4.25,"demandaPropagandaInternet":160,"demandaTotalPropaganda":290,"qtdProdutosEstoqueFornecedor1":600,"qtdProdutosEstoqueFornecedor2":1200,"qtdProdutosEstoqueFornecedor3":850,"tamanhoEstabelecimento":"GRANDE","qtdCaixas":8,"qtdFuncionarios":18,"pontosCapacidadeInstalada":167.66666666666666,"notaCapacidadeInstalada":4.795042897998093,"demandaCapacidadeInstalada":545},{"identificacaoJogada":"3","demandaTotalJogada":926,"preco":13.99,"notaPreco":3.4998749061796346,"demandaPreco":324,"investimentoPropagandaRadio":4000.0,"notaPropagandaRadio":3.085714285714286,"demandaPropagandaRadio":108,"investimentoPropagandaJornal":4000.0,"notaPropagandaJornal":2.238095238095238,"demandaPropagandaJornal":58,"investimentoPropagandaTV":4000.0,"notaPropagandaTV":2.111111111111111,"demandaPropagandaTV":64,"investimentoPropagandaInternet":9000.0,"notaPropagandaInternet":5.0,"demandaPropagandaInternet":222,"demandaTotalPropaganda":452,"qtdProdutosEstoqueFornecedor1":750,"qtdProdutosEstoqueFornecedor2":1000,"qtdProdutosEstoqueFornecedor3":950,"tamanhoEstabelecimento":"MEDIO","qtdCaixas":4,"qtdFuncionarios":8,"pontosCapacidadeInstalada":112.0,"notaCapacidadeInstalada":2.6330846540016988,"demandaCapacidadeInstalada":164}]}],"variavelMicroeconomica":{"preco":45.0,"fatorPenalidadePreco":3,"propaganda":35.0,"porcentagemPropagandaRadio":20.0,"valorMinimoPropagandaRadio":350.0,"proporcaoCrescimentoPropagandaRadio":5.0,"porcentagemPropagandaJornal":15.0,"valorMinimoPropagandaJornal":750.0,"proporcaoCrescimentoPropagandaJornal":3.5,"porcentagemPropagandaTV":30.0,"valorMinimoPropagandaTV":1500.0,"proporcaoCrescimentoPropagandaTV":1.5,"porcentagemPropagandaInternet":35.0,"valorMinimoPropagandaInternet":1000.0,"proporcaoCrescimentoPropagandaInternet":2.0,"confiabilidadeProduto1":15,"confiabilidadeProduto2":25,"confiabilidadeProduto3":35,"capacidadeInstalada":20.0,"tamanhoEstabelecimentoPequeno":50.0,"pesoTamanhoEstabelecimentoPequeno":1.0,"qtdMaxCaixasEstabelecimentoPequeno":3,"tamanhoEstabelecimentoMedio":100.0,"pesoTamanhoEstabelecimentoMedio":2.0,"qtdMaxCaixasEstabelecimentoMedio":6,"tamanhoEstabelecimentoGrande":150.0,"pesoTamanhoEstabelecimentoGrande":3.0,"qtdMaxCaixasEstabelecimentoGrande":10,"pesoCaixas":3.0,"pesoFuncionarios":1.0},"variavelMacroeconomica":{"taxaBasicaJuros":{"1":3.7},"fatorAjuste":1.0}}